calcexptime/__init__.py
calcexptime/__main__.py
calcexptime/functions.py
calcexptime-1.0.2.dist-info/LICENSE.txt
calcexptime-1.0.2.dist-info/METADATA
calcexptime-1.0.2.dist-info/WHEEL
calcexptime-1.0.2.dist-info/top_level.txt
calcexptime-1.0.2.dist-info/RECORD
