Metadata-Version: 2.1
Name: calcexptime
Version: 1.0.2
Summary: Calculates the duration of an experiment and tells when it does end.
Home-page: https://github.com/MetallerTM/calcexptime
Author: Francesco Bruno
Author-email: bruno@cerm.unifi.it
License: LICENSE.txt
Platform: UNKNOWN
Classifier: Programming Language :: Python :: 3
Classifier: Operating System :: OS Independent
Classifier: License :: OSI Approved :: MIT License
Requires-Python: >=3.6
License-File: LICENSE.txt
